counter_60.v/counter_4b.v
module counter_4b (
    input clk,
    input rstn,
    output reg [5:0] nums, 
    output reg cout
);

initial begin
    nums <= 6'b000000;
    cout <= 0;
end

always @(posedge clk or negedge rstn) begin
    if (!rstn) 
        begin
            nums <= 6'b000000;
        end
    else if(nums == 6'b111100)
        begin
            cout <= 1;
            nums <= 6'b000000;
        end
    else
        begin
            cout <= 0;
            nums <= nums + 1;
        end
end

endmodule //4b_counter

counter_60.v/tb_counter_4b.v
//~ `New testbench
`timescale  1ns / 1ns
`include "counter_4b.v"

module tb_counter_4b;

// counter_4b Parameters
parameter PERIOD  = 10;


// counter_4b Inputs
reg   clk                                  = 1 ;
reg   rstn                                 = 1 ;

// counter_4b Outputs
wire  [5:0]  nums                          ;
wire  cout                                 ;


initial
begin
    forever #(PERIOD/2)  clk=~clk;
end

initial
begin
    #(PERIOD*2) rstn  =  1;
end

counter_4b  u_counter_4b (
    .clk                     ( clk         ),
    .rstn                    ( rstn        ),

    .nums                    ( nums  [5:0] ),
    .cout                    ( cout        )
);

initial
begin
    $dumpfile("wave.vcd");        //生成的vcd文件名称
    $dumpvars;
    
    rstn <= 0;
    #10
    rstn <=1;
    #702
    rstn <= 0;
    #4
    rstn <=1;
    #200
    $finish;
end

endmodule

counter_60.v/wave.vcd
$date
	Thu Nov 16 20:38:57 2023
$end
$version
	Icarus Verilog
$end
$timescale
	1ns
$end
$scope module tb_counter_4b $end
$var wire 6 ! nums [5:0] $end
$var wire 1 " cout $end
$var parameter 32 # PERIOD $end
$var reg 1 $ clk $end
$var reg 1 % rstn $end
$scope module u_counter_4b $end
$var wire 1 $ clk $end
$var wire 1 % rstn $end
$var reg 1 " cout $end
$var reg 6 & nums [5:0] $end
$upscope $end
$upscope $end
$enddefinitions $end
$comment Show the parameter values. $end
$dumpall
b1010 #
$end
#0
$dumpvars
b0 &
0%
1$
0"
b0 !
$end
#5
0$
#10
1%
1$
#15
0$
#20
b1 !
b1 &
1$
#25
0$
#30
b10 !
b10 &
1$
#35
0$
#40
b11 !
b11 &
1$
#45
0$
#50
b100 !
b100 &
1$
#55
0$
#60
b101 !
b101 &
1$
#65
0$
#70
b110 !
b110 &
1$
#75
0$
#80
b111 !
b111 &
1$
#85
0$
#90
b1000 !
b1000 &
1$
#95
0$
#100
b1001 !
b1001 &
1$
#105
0$
#110
b1010 !
b1010 &
1$
#115
0$
#120
b1011 !
b1011 &
1$
#125
0$
#130
b1100 !
b1100 &
1$
#135
0$
#140
b1101 !
b1101 &
1$
#145
0$
#150
b1110 !
b1110 &
1$
#155
0$
#160
b1111 !
b1111 &
1$
#165
0$
#170
b10000 !
b10000 &
1$
#175
0$
#180
b10001 !
b10001 &
1$
#185
0$
#190
b10010 !
b10010 &
1$
#195
0$
#200
b10011 !
b10011 &
1$
#205
0$
#210
b10100 !
b10100 &
1$
#215
0$
#220
b10101 !
b10101 &
1$
#225
0$
#230
b10110 !
b10110 &
1$
#235
0$
#240
b10111 !
b10111 &
1$
#245
0$
#250
b11000 !
b11000 &
1$
#255
0$
#260
b11001 !
b11001 &
1$
#265
0$
#270
b11010 !
b11010 &
1$
#275
0$
#280
b11011 !
b11011 &
1$
#285
0$
#290
b11100 !
b11100 &
1$
#295
0$
#300
b11101 !
b11101 &
1$
#305
0$
#310
b11110 !
b11110 &
1$
#315
0$
#320
b11111 !
b11111 &
1$
#325
0$
#330
b100000 !
b100000 &
1$
#335
0$
#340
b100001 !
b100001 &
1$
#345
0$
#350
b100010 !
b100010 &
1$
#355
0$
#360
b100011 !
b100011 &
1$
#365
0$
#370
b100100 !
b100100 &
1$
#375
0$
#380
b100101 !
b100101 &
1$
#385
0$
#390
b100110 !
b100110 &
1$
#395
0$
#400
b100111 !
b100111 &
1$
#405
0$
#410
b101000 !
b101000 &
1$
#415
0$
#420
b101001 !
b101001 &
1$
#425
0$
#430
b101010 !
b101010 &
1$
#435
0$
#440
b101011 !
b101011 &
1$
#445
0$
#450
b101100 !
b101100 &
1$
#455
0$
#460
b101101 !
b101101 &
1$
#465
0$
#470
b101110 !
b101110 &
1$
#475
0$
#480
b101111 !
b101111 &
1$
#485
0$
#490
b110000 !
b110000 &
1$
#495
0$
#500
b110001 !
b110001 &
1$
#505
0$
#510
b110010 !
b110010 &
1$
#515
0$
#520
b110011 !
b110011 &
1$
#525
0$
#530
b110100 !
b110100 &
1$
#535
0$
#540
b110101 !
b110101 &
1$
#545
0$
#550
b110110 !
b110110 &
1$
#555
0$
#560
b110111 !
b110111 &
1$
#565
0$
#570
b111000 !
b111000 &
1$
#575
0$
#580
b111001 !
b111001 &
1$
#585
0$
#590
b111010 !
b111010 &
1$
#595
0$
#600
b111011 !
b111011 &
1$
#605
0$
#610
b111100 !
b111100 &
1$
#615
0$
#620
b0 !
b0 &
1"
1$
#625
0$
#630
b1 !
b1 &
0"
1$
#635
0$
#640
b10 !
b10 &
1$
#645
0$
#650
b11 !
b11 &
1$
#655
0$
#660
b100 !
b100 &
1$
#665
0$
#670
b101 !
b101 &
1$
#675
0$
#680
b110 !
b110 &
1$
#685
0$
#690
b111 !
b111 &
1$
#695
0$
#700
b1000 !
b1000 &
1$
#705
0$
#710
b1001 !
b1001 &
1$
#712
b0 !
b0 &
0%
#715
0$
#716
1%
#720
b1 !
b1 &
1$
#725
0$
#730
b10 !
b10 &
1$
#735
0$
#740
b11 !
b11 &
1$
#745
0$
#750
b100 !
b100 &
1$
#755
0$
#760
b101 !
b101 &
1$
#765
0$
#770
b110 !
b110 &
1$
#775
0$
#780
b111 !
b111 &
1$
#785
0$
#790
b1000 !
b1000 &
1$
#795
0$
#800
b1001 !
b1001 &
1$
#805
0$
#810
b1010 !
b1010 &
1$
#815
0$
#820
b1011 !
b1011 &
1$
#825
0$
#830
b1100 !
b1100 &
1$
#835
0$
#840
b1101 !
b1101 &
1$
#845
0$
#850
b1110 !
b1110 &
1$
#855
0$
#860
b1111 !
b1111 &
1$
#865
0$
#870
b10000 !
b10000 &
1$
#875
0$
#880
b10001 !
b10001 &
1$
#885
0$
#890
b10010 !
b10010 &
1$
#895
0$
#900
b10011 !
b10011 &
1$
#905
0$
#910
b10100 !
b10100 &
1$
