PWM/PWM.v
module PWM(
    timer, clk, out, rstn
);
    input clk;
    input rstn;
    output out;
    output [31 : 0] timer;
    reg out;
    reg [31 : 0]timer ;
    
    initial begin
        timer <= 32'b0;
        out <= 1'b0;
    end

    always @(posedge clk or negedge rstn) begin
        if (!rstn) begin
            timer <= 32'd0;
        end
        else if(timer == 32'b1111) begin
            timer <= 32'd0;
        end
        else if(timer == 32'b11) begin
            out <= 32'd1;
            timer <= timer + 32'b1;
        end
        else if(timer == 32'b111) begin
            out <= 32'd0;
            timer <= timer + 32'b1;
        end
        else begin
            timer <= timer + 32'b1;
        end
    end
endmodule

PWM/PWM_tb.v
//~ `New testbench
`timescale  1ns / 1ps
`include "PWM.v"

module tb_PWM;

// PWM Parameters
parameter PERIOD  = 2;


// PWM Inputs
reg   clk                                  = 0 ;
reg   rstn                                 = 0 ;

// PWM Outputs
wire  out                                  ;
wire  [31 : 0]  timer                      ;


initial
begin
    forever #(PERIOD/2)  clk=~clk;
end

initial
begin
    #(PERIOD*2) rstn  =  1;
end

PWM  u_PWM (
    .clk                     ( clk             ),
    .rstn                    ( rstn            ),

    .out                     ( out             ),
    .timer                   ( timer  [31 : 0] )
);

initial
begin
    $dumpfile("wave.vcd");        //生成的vcd文件名称
    $dumpvars;
    #100000
    $finish;
end

endmodule

PWM/wave.vcd
$date
	Thu Dec  7 19:23:29 2023
$end
$version
	Icarus Verilog
$end
$timescale
	1ps
$end
$scope module tb_PWM $end
$var wire 32 ! timer [31:0] $end
$var wire 1 " out $end
$var parameter 32 # PERIOD $end
$var reg 1 $ clk $end
$var reg 1 % rstn $end
$scope module u_PWM $end
$var wire 1 $ clk $end
$var wire 1 % rstn $end
$var reg 1 " out $end
$var reg 32 & timer [31:0] $end
$upscope $end
$upscope $end
$enddefinitions $end
$comment Show the parameter values. $end
$dumpall
b10 #
$end
#0
$dumpvars
b0 &
0%
0$
0"
b0 !
$end
#1000
1$
#2000
0$
#3000
1$
#4000
0$
1%
#5000
b1 !
b1 &
1$
#6000
0$
#7000
b10 !
b10 &
1$
#8000
0$
#9000
b11 !
b11 &
1$
#10000
0$
#11000
b100 !
b100 &
1"
1$
#12000
0$
#13000
b101 !
b101 &
1$
#14000
0$
#15000
b110 !
b110 &
1$
#16000
0$
#17000
b111 !
b111 &
1$
#18000
0$
#19000
b1000 !
b1000 &
0"
1$
#20000
0$
#21000
b1001 !
b1001 &
1$
#22000
0$
#23000
b1010 !
b1010 &
1$
#24000
0$
#25000
b1011 !
b1011 &
1$
#26000
0$
#27000
b1100 !
b1100 &
1$
#28000
0$
#29000
b1101 !
b1101 &
1$
#30000
0$
#31000
b1110 !
b1110 &
1$
#32000
0$
#33000
b1111 !
b1111 &
1$
#34000
0$
#35000
b0 !
b0 &
1$
#36000
0$
#37000
b1 !
b1 &
1$
#38000
0$
#39000
b10 !
b10 &
1$
#40000
0$
#41000
b11 !
b11 &
1$
#42000
0$
#43000
b100 !
b100 &
1"
1$
#44000
0$
#45000
b101 !
b101 &
1$
#46000
0$
#47000
b110 !
b110 &
1$
#48000
0$
#49000
b111 !
b111 &
1$
#50000
0$
#51000
b1000 !
b1000 &
0"
1$
#52000
0$
#53000
b1001 !
b1001 &
1$
#54000
0$
#55000
b1010 !
b1010 &
1$
#56000
0$
#57000
b1011 !
b1011 &
1$
#58000
0$
#59000
b1100 !
b1100 &
1$
#60000
0$
#61000
b1101 !
b1101 &
1$
#62000
0$
#63000
b1110 !
b1110 &
1$
#64000
0$
#65000
b1111 !
b1111 &
1$
#66000
0$
#67000
b0 !
b0 &
1$
#68000
0$
#69000
b1 !
b1 &
1$
#70000
0$
#71000
b10 !
b10 &
1$
#72000
0$
#73000
b11 !
b11 &
1$
#74000
0$
#75000
b100 !
b100 &
1"
1$
#76000
0$
#77000
b101 !
b101 &
1$
#78000
0$
#79000
b110 !
b110 &
1$
#80000
0$
#81000
b111 !
b111 &
1$
#82000
0$
#83000
b1000 !
b1000 &
0"
1$
#84000
0$
#85000
b1001 !
b1001 &
1$
#86000
0$
#87000
b1010 !
b1010 &
1$
#88000
0$
#89000
b1011 !
b1011 &
1$
#90000
0$
#91000
b1100 !
b1100 &
1$
#92000
0$
#93000
b1101 !
b1101 &
1$
#94000
0$
#95000
b1110 !
b1110 &
1$
#96000
0$
#97000
b1111 !
b1111 &
1$
#98000
0$
#99000
b0 !
b0 &
1$
#100000
0$
#101000
b1 !
b1 &
1$
#102000
0$
#103000
b10 !
b10 &
1$
#104000
0$
#105000
b11 !
b11 &
1$
#106000
0$
#107000
b100 !
b100 &
1"
1$
#108000
0$
#109000
b101 !
b101 &
1$
#110000
0$
#111000
b110 !
b110 &
1$
#112000
0$
#113000
b111 !
b111 &
1$
#114000
0$
#115000
b1000 !
b1000 &
0"
1$
#116000
0$
#117000
b1001 !
b1001 &
1$
#118000
0$
#119000
b1010 !
b1010 &
1$
#120000
0$
#121000
b1011 !
b1011 &
1$
#122000
0$
#123000
b1100 !
b1100 &
1$
#124000
0$
#125000
b1101 !
b1101 &
1$
#126000
0$
#127000
b1110 !
b1110 &
1$
#128000
0$
#129000
b1111 !
b1111 &
1$
#130000
0$
#131000
b0 !
b0 &
1$
#132000
0$
#133000
b1 !
b1 &
1$
#134000
0$
#135000
b10 !
b10 &
1$
#136000
0$
#137000
b11 !
b11 &
1$
#138000
0$
#139000
b100 !
b100 &
1"
1$
#140000
0$
#141000
b101 !
b101 &
1$
#142000
0$
#143000
b110 !
b110 &
1$
#144000
0$
#145000
b111 !
b111 &
1$
#146000
0$
#147000
b1000 !
b1000 &
0"
1$
#148000
0$
#149000
b1001 !
b1001 &
1$
#150000
0$
#151000
b1010 !
b1010 &
1$
#152000
0$
#153000
b1011 !
b1011 &
1$
#154000
0$
#155000
b1100 !
b1100 &
1$
#156000
0$
#157000
b1101 !
b1101 &
1$
#158000
0$
#159000
b1110 !
b1110 &
1$
#160000
0$
#161000
b1111 !
b1111 &
1$
#162000
0$
#163000
b0 !
b0 &
1$
#164000
0$
#165000
b1 !
b1 &
1$
#166000
0$
#167000
b10 !
b10 &
1$
#168000
0$
#169000
b11 !
b11 &
1$
#170000
0$
#171000
b100 !
b100 &
1"
1$
#172000
0$
#173000
b101 !
b101 &
1$
#174000
0$
#175000
b110 !
b110 &
1$
#176000
0$
#177000
b111 !
b111 &
1$
#178000
0$
#179000
b1000 !
b1000 &
0"
1$
#180000
0$
#181000
b1001 !
b1001 &
1$
#182000
0$
#183000
b1010 !
b1010 &
1$
#184000
0$
#185000
b1011 !
b1011 &
1$
#186000
0$
#187000
b1100 !
b1100 &
1$
#188000
0$
#189000
b1101 !
b1101 &
1$
#190000
0$
#191000
b1110 !
b1110 &
1$
#192000
0$
#193000
b1111 !
b1111 &
1$
#194000
0$
#195000
b0 !
b0 &
1$
#196000
0$
#197000
b1 !
b1 &
1$
#198000
0$
#199000
b10 !
b10 &
1$
#200000
0$
#201000
b11 !
b11 &
1$
#202000
0$
#203000
b100 !
b100 &
1"
1$
#204000
0$
#205000
b101 !
b101 &
1$
#206000
0$
#207000
b110 !
b110 &
1$
#208000
0$
#209000
b111 !
b111 &
1$
#210000
0$
#211000
b1000 !
b1000 &
0"
1$
#212000
0$
#213000
b1001 !
b1001 &
1$
#214000
0$
#215000
b1010 !
b1010 &
1$
#216000
0$
#217000
b1011 !
b1011 &
1$
#218000
0$
#219000
b1100 !
b1100 &
1$
#220000
0$
#221000
b1101 !
b1101 &
1$
#222000
0$
#223000
b1110 !
b1110 &
1$
#224000
0$
#225000
b1111 !
b1111 &
1$
#226000
0$
#227000
b0 !
b0 &
1$
#228000
0$
#229000
b1 !
b1 &
1$
#230000
0$
#231000
b10 !
b10 &
1$
#232000
0$
#233000
b11 !
b11 &
1$
#234000
0$
#235000
b100 !
b100 &
1"
1$
#236000
0$
#237000
b101 !
b101 &
1$
#238000
0$
#239000
b110 !
b110 &
1$
#240000
0$
#241000
b111 !
b111 &
1$
#242000
0$
#243000
b1000 !
b1000 &
0"
1$
#244000
0$
#245000
b1001 !
b1001 &
1$
#246000
0$
#247000
b1010 !
b1010 &
1$
#248000
0$
#249000
b1011 !
b1011 &
1$
#250000
0$
#251000
b1100 !
b1100 &
1$
#252000
0$
#253000
b1101 !
b1101 &
1$
#254000
0$
#255000
b1110 !
b1110 &
1$
#256000
0$
#257000
b1111 !
b1111 &
1$
#258000
0$
#259000
b0 !
b0 &
1$
#260000
0$
#261000
b1 !
b1 &
1$
#262000
0$
#263000
b10 !
b10 &
1$
#264000
0$
#265000
b11 !
b11 &
1$
#266000
0$
#267000
b100 !
b100 &
1"
1$
#268000
0$
#269000
b101 !
b101 &
1$
#270000
0$
#271000
b110 !
b110 &
1$
#272000
0$
#273000
b111 !
b111 &
1$
#274000
0$
#275000
b1000 !
b1000 &
0"
1$
#276000
0$
#277000
b1001 !
b1001 &
1$
#278000
0$
#279000
b1010 !
b1010 &
1$
#280000
0$
#281000
b1011 !
b1011 &
1$
#282000
0$
#283000
b1100 !
b1100 &
1$
#284000
0$
#285000
b1101 !
b1101 &
1$
#286000
0$
#287000
b1110 !
b1110 &
1$
#288000
0$
#289000
b1111 !
b1111 &
1$
#290000
0$
#291000
b0 !
b0 &
1$
#292000
0$
#293000
b1 !
b1 &
1$
#294000
0$
#295000
b10 !
b10 &
1$
#296000
0$
#297000
b11 !
b11 &
1$
#298000
0$
#299000
b100 !
b100 &
1"
1$
#300000
0$
#301000
b101 !
b101 &
1$
#302000
0$
#303000
b110 !
b110 &
1$
#304000
0$
#305000
b111 !
b111 &
1$
#306000
0$
#307000
b1000 !
b1000 &
0"
1$
#308000
0$
#309000
b1001 !
b1001 &
1$
#310000
0$
#311000
b1010 !
b1010 &
1$
#312000
0$
#313000
b1011 !
b1011 &
1$
#314000
0$
#315000
b1100 !
b1100 &
1$
#316000
0$
#317000
b1101 !
b1101 &
1$
#318000
0$
#319000
b1110 !
b1110 &
1$
#320000
0$
#321000
b1111 !
b1111 &
1$
#322000
0$
#323000
b0 !
b0 &
1$
#324000
0$
#325000
b1 !
b1 &
1$
#326000
0$
#327000
b10 !
b10 &
1$
#328000
0$
#329000
b11 !
b11 &
1$
#330000
0$
#331000
b100 !
b100 &
1"
1$
#332000
0$
#333000
b101 !
b101 &
1$
#334000
0$
#335000
b110 !
b110 &
1$
#336000
0$
#337000
b111 !
b111 &
1$
#338000
0$
#339000
b1000 !
b1000 &
0"
1$
#340000
0$
#341000
b1001 !
b1001 &
1$
#342000
0$
#343000
b1010 !
b1010 &
1$
#344000
0$
#345000
b1011 !
b1011 &
1$
#346000
0$
#347000
b1100 !
b1100 &
1$
#348000
0$
#349000
b1101 !
b1101 &
1$
#350000
0$
#351000
b1110 !
b1110 &
1$
#352000
0$
#353000
b1111 !
b1111 &
1$
#354000
0$
#355000
b0 !
b0 &
1$
#356000
0$
#357000
b1 !
b1 &
1$
#358000
0$
#359000
b10 !
b10 &
1$
#360000
0$
#361000
b11 !
b11 &
1$
#362000
0$
#363000
b100 !
b100 &
1"
1$
#364000
0$
#365000
b101 !
b101 &
1$
#366000
0$
#367000
b110 !
b110 &
1$
#368000
0$
#369000
b111 !
b111 &
1$
#370000
0$
#371000
b1000 !
b1000 &
0"
1$
#372000
0$
#373000
b1001 !
b1001 &
1$
#374000
0$
#375000
b1010 !
b1010 &
1$
#376000
0$
#377000
b1011 !
b1011 &
1$
#378000
0$
#379000
b1100 !
b1100 &
1$
#380000
0$
#381000
b1101 !
b1101 &
1$
#382000
0$
#383000
b1110 !
b1110 &
1$
#384000
0$
#385000
b1111 !
b1111 &
1$
#386000
0$
#387000
b0 !
b0 &
1$
#388000
0$
#389000
b1 !
b1 &
1$
#390000
0$
#391000
b10 !
b10 &
1$
#392000
0$
#393000
b11 !
b11 &
1$
#394000
0$
#395000
b100 !
b100 &
1"
1$
#396000
0$
#397000
b101 !
b101 &
1$
#398000
0$
#399000
b110 !
b110 &
1$
#400000
0$
#401000
b111 !
b111 &
1$
#402000
0$
#403000
b1000 !
b1000 &
0"
1$
#404000
0$
#405000
b1001 !
b1001 &
1$
#406000
0$
#407000
b1010 !
b1010 &
1$
#408000
0$
#409000
b1011 !
b1011 &
1$
#410000
0$
#411000
b1100 !
b1100 &
1$
#412000
0$
#413000
b1101 !
b1101 &
1$
#414000
0$
#415000
b1110 !
b1110 &
1$
#416000
0$
#417000
b1111 !
b1111 &
1$
#418000
0$
#419000
b0 !
b0 &
1$
#420000
0$
#421000
b1 !
b1 &
1$
#422000
0$
#423000
b10 !
b10 &
1$
#424000
0$
#425000
b11 !
b11 &
1$
#426000
0$
#427000
b100 !
b100 &
1"
1$
#428000
0$
#429000
b101 !
b101 &
1$
#430000
0$
#431000
b110 !
b110 &
1$
#432000
0$
#433000
b111 !
b111 &
1$
#434000
0$
#435000
b1000 !
b1000 &
0"
1$
#436000
0$
#437000
b1001 !
b1001 &
1$
#438000
0$
#439000
b1010 !
b1010 &
1$
#440000
0$
#441000
b1011 !
b1011 &
1$
#442000
0$
#443000
b1100 !
b1100 &
1$
#444000
0$
#445000
b1101 !
b1101 &
1$
#446000
0$
#447000
b1110 !
b1110 &
1$
#448000
0$
#449000
b1111 !
b1111 &
1$
#450000
0$
#451000
b0 !
b0 &
1$
#452000
0$
#453000
b1 !
b1 &
1$
#454000
0$
#455000
b10 !
b10 &
1$
#456000
0$
#457000
b11 !
b11 &
1$
#458000
0$
#459000
b100 !
b100 &
1"
1$
#460000
0$
#461000
b101 !
b101 &
1$
#462000
0$
#463000
b110 !
b110 &
1$
#464000
0$
#465000
b111 !
b111 &
1$
#466000
0$
#467000
b1000 !
b1000 &
0"
1$
#468000
0$
#469000
b1001 !
b1001 &
1$
#470000
0$
#471000
b1010 !
b1010 &
1$
#472000
0$
#473000
b1011 !
b1011 &
1$
#474000
0$
#475000
b1100 !
b1100 &
1$
#476000
0$
#477000
b1101 !
b1101 &
1$
#478000
0$
#479000
b1110 !
b1110 &
1$
#480000
0$
#481000
b1111 !
b1111 &
1$
#482000
0$
#483000
b0 !
b0 &
1$
#484000
0$
#485000
b1 !
b1 &
1$
#486000
0$
#487000
b10 !
b10 &
1$
#488000
0$
#489000
b11 !
b11 &
1$
#490000
0$
#491000
b100 !
b100 &
1"
1$
#492000
0$
#493000
b101 !
b101 &
1$
#494000
0$
#495000
b110 !
b110 &
1$
#496000
0$
#497000
b111 !
b111 &
1$
#498000
0$
#499000
b1000 !
b1000 &
0"
1$
#500000
0$
#501000
b1001 !
b1001 &
1$
#502000
0$
#503000
b1010 !
b1010 &
1$
#504000
0$
#505000
b1011 !
b1011 &
1$
#506000
0$
#507000
b1100 !
b1100 &
1$
#508000
0$
#509000
b1101 !
b1101 &
1$
#510000
0$
#511000
b1110 !
b1110 &
1$
#512000
0$
#513000
b1111 !
b1111 &
1$
#514000
0$
#515000
b0 !
b0 &
1$
#516000
0$
#517000
b1 !
b1 &
1$
#518000
0$
#519000
b10 !
b10 &
1$
#520000
0$
#521000
b11 !
b11 &
1$
#522000
0$
#523000
b100 !
b100 &
1"
1$
#524000
0$
#525000
b101 !
b101 &
1$
#526000
0$
#527000
b110 !
b110 &
1$
#528000
0$
#529000
b111 !
b111 &
1$
#530000
0$
#531000
b1000 !
b1000 &
0"
1$
#532000
0$
#533000
b1001 !
b1001 &
1$
#534000
0$
#535000
b1010 !
b1010 &
1$
#536000
0$
#537000
b1011 !
b1011 &
1$
#538000
0$
#539000
b1100 !
b1100 &
1$
#540000
0$
#541000
b1101 !
b1101 &
1$
#542000
0$
#543000
b1110 !
b1110 &
1$
#544000
0$
#545000
b1111 !
b1111 &
1$
#546000
0$
#547000
b0 !
b0 &
1$
#548000
0$
#549000
b1 !
b1 &
1$
#550000
0$
#551000
b10 !
b10 &
1$
#552000
0$
#553000
b11 !
b11 &
1$
#554000
0$
#555000
b100 !
b100 &
1"
1$
#556000
0$
#557000
b101 !
b101 &
1$
#558000
0$
#559000
b110 !
b110 &
1$
#560000
0$
#561000
b111 !
b111 &
1$
#562000
0$
#563000
b1000 !
b1000 &
0"
1$
#564000
0$
#565000
b1001 !
b1001 &
1$
#566000
0$
#567000
b1010 !
b1010 &
1$
#568000
0$
#569000
b1011 !
b1011 &
1$
#570000
0$
#571000
b1100 !
b1100 &
1$
#572000
0$
#573000
b1101 !
b1101 &
1$
#574000
0$
#575000
b1110 !
b1110 &
1$
#576000
0$
#577000
b1111 !
b1111 &
1$
#578000
0$
#579000
b0 !
b0 &
1$
#580000
0$
#581000
b1 !
b1 &
1$
#582000
0$
#583000
b10 !
b10 &
1$
#584000
0$
#585000
b11 !
b11 &
1$
#586000
0$
#587000
b100 !
b100 &
1"
1$
#588000
0$
#589000
b101 !
b101 &
1$
#590000
0$
#591000
b110 !
b110 &
1$
#592000
0$
#593000
b111 !
b111 &
1$
#594000
0$
#595000
b1000 !
b1000 &
0"
1$
#596000
0$
#597000
b1001 !
b1001 &
1$
#598000
0$
#599000
b1010 !
b1010 &
1$
#600000
0$
#601000
b1011 !
b1011 &
1$
#602000
0$
#603000
b1100 !
b1100 &
1$
#604000
0$
#605000
b1101 !
b1101 &
1$
#606000
0$
#607000
b1110 !
b1110 &
1$
#608000
0$
#609000
b1111 !
b1111 &
1$
#610000
0$
#611000
b0 !
b0 &
1$
#612000
0$
#613000
b1 !
b1 &
1$
#614000
0$
#615000
b10 !
b10 &
1$
#616000
0$
#617000
b11 !
b11 &
1$
#618000
0$
#619000
b100 !
b100 &
1"
1$
#620000
0$
#621000
b101 !
b101 &
1$
#622000
0$
#623000
b110 !
b110 &
1$
#624000
0$
#625000
b111 !
b111 &
1$
#626000
0$
#627000
b1000 !
b1000 &
0"
1$
#628000
0$
#629000
b1001 !
b1001 &
1$
#630000
0$
#631000
b1010 !
b1010 &
1$
#632000
0$
#633000
b1011 !
b1011 &
1$
#634000
0$
#635000
b1100 !
b1100 &
1$
#636000
0$
#637000
b1101 !
b1101 &
1$
#638000
0$
#639000
b1110 !
b1110 &
1$
#640000
0$
#641000
b1111 !
b1111 &
1$
#642000
0$
#643000
b0 !
b0 &
1$
#644000
0$
#645000
b1 !
b1 &
1$
#646000
0$
#647000
b10 !
b10 &
1$
#648000
0$
#649000
b11 !
b11 &
1$
#650000
0$
#651000
b100 !
b100 &
1"
1$
#652000
0$
#653000
b101 !
b101 &
1$
#654000
0$
#655000
b110 !
b110 &
1$
#656000
0$
#657000
b111 !
b111 &
1$
#658000
0$
#659000
b1000 !
b1000 &
0"
1$
#660000
0$
#661000
b1001 !
b1001 &
1$
#662000
0$
#663000
b1010 !
b1010 &
1$
#664000
0$
#665000
b1011 !
b1011 &
1$
#666000
0$
#667000
b1100 !
b1100 &
1$
#668000
0$
#669000
b1101 !
b1101 &
1$
#670000
0$
#671000
b1110 !
b1110 &
1$
#672000
0$
#673000
b1111 !
b1111 &
1$
#674000
0$
#675000
b0 !
b0 &
1$
#676000
0$
#677000
b1 !
b1 &
1$
#678000
0$
#679000
b10 !
b10 &
1$
#680000
0$
#681000
b11 !
b11 &
1$
#682000
0$
#683000
b100 !
b100 &
1"
1$
#684000
0$
#685000
b101 !
b101 &
1$
#686000
0$
#687000
b110 !
b110 &
1$
#688000
0$
#689000
b111 !
b111 &
1$
#690000
0$
#691000
b1000 !
b1000 &
0"
1$
#692000
0$
#693000
b1001 !
b1001 &
1$
#694000
0$
#695000
b1010 !
b1010 &
1$
#696000
0$
#697000
b1011 !
b1011 &
1$
#698000
0$
#699000
b1100 !
b1100 &
1$
#700000
0$
#701000
b1101 !
b1101 &
1$
#702000
0$
#703000
b1110 !
b1110 &
1$
#704000
0$
#705000
b1111 !
b1111 &
1$
#706000
0$
#707000
b0 !
b0 &
1$
#708000
0$
#709000
b1 !
b1 &
1$
#710000
0$
#711000
b10 !
b10 &
1$
#712000
0$
#713000
b11 !
b11 &
1$
#714000
0$
#715000
b100 !
b100 &
1"
1$
#716000
0$
#717000
b101 !
b101 &
1$
#718000
0$
#719000
b110 !
b110 &
1$
#720000
0$
#721000
b111 !
b111 &
1$
#722000
0$
#723000
b1000 !
b1000 &
0"
1$
#724000
0$
#725000
b1001 !
b1001 &
1$
#726000
0$
#727000
b1010 !
b1010 &
1$
#728000
0$
#729000
b1011 !
b1011 &
1$
#730000
0$
#731000
b1100 !
b1100 &
1$
#732000
0$
#733000
b1101 !
b1101 &
1$
#734000
0$
#735000
b1110 !
b1110 &
1$
#736000
0$
#737000
b1111 !
b1111 &
1$
#738000
0$
#739000
b0 !
b0 &
1$
#740000
0$
#741000
b1 !
b1 &
1$
#742000
0$
#743000
b10 !
b10 &
1$
#744000
0$
#745000
b11 !
b11 &
1$
#746000
0$
#747000
b100 !
b100 &
1"
1$
#748000
0$
#749000
b101 !
b101 &
1$
#750000
0$
#751000
b110 !
b110 &
1$
#752000
0$
#753000
b111 !
b111 &
1$
#754000
0$
#755000
b1000 !
b1000 &
0"
1$
#756000
0$
#757000
b1001 !
b1001 &
1$
#758000
0$
#759000
b1010 !
b1010 &
1$
#760000
0$
#761000
b1011 !
b1011 &
1$
#762000
0$
#763000
b1100 !
b1100 &
1$
#764000
0$
#765000
b1101 !
b1101 &
1$
#766000
0$
#767000
b1110 !
b1110 &
1$
#768000
0$
#769000
b1111 !
b1111 &
1$
#770000
0$
#771000
b0 !
b0 &
1$
#772000
0$
#773000
b1 !
b1 &
1$
#774000
0$
#775000
b10 !
b10 &
1$
#776000
0$
#777000
b11 !
b11 &
1$
#778000
0$
#779000
b100 !
b100 &
1"
1$
#780000
0$
#781000
b101 !
b101 &
1$
#782000
0$
#783000
b110 !
b110 &
1$
#784000
0$
#785000
b111 !
b111 &
1$
#786000
0$
#787000
b1000 !
b1000 &
0"
1$
#788000
0$
#789000
b1001 !
b1001 &
1$
#790000
0$
#791000
b1010 !
b1010 &
1$
#792000
0$
#793000
b1011 !
b1011 &
1$
#794000
0$
#795000
b1100 !
b1100 &
1$
#796000
0$
#797000
b1101 !
b1101 &
1$
#798000
0$
#799000
b1110 !
b1110 &
1$
#800000
0$
#801000
b1111 !
b1111 &
1$
#802000
0$
#803000
b0 !
b0 &
1$
#804000
0$
#805000
b1 !
b1 &
1$
#806000
0$
#807000
b10 !
b10 &
1$
#808000
0$
#809000
b11 !
b11 &
1$
#810000
0$
#811000
b100 !
b100 &
1"
1$
#812000
0$
#813000
b101 !
b101 &
1$
#814000
0$
#815000
b110 !
b110 &
1$
#816000
0$
#817000
b111 !
b111 &
1$
#818000
0$
#819000
b1000 !
b1000 &
0"
1$
#820000
0$
#821000
b1001 !
b1001 &
1$
#822000
0$
#823000
b1010 !
b1010 &
1$
#824000
0$
#825000
b1011 !
b1011 &
1$
#826000
0$
#827000
b1100 !
b1100 &
1$
#828000
0$
#829000
b1101 !
b1101 &
1$
#830000
0$
#831000
b1110 !
b1110 &
1$
#832000
0$
#833000
b1111 !
b1111 &
1$
#834000
0$
#835000
b0 !
b0 &
1$
#836000
0$
#837000
b1 !
b1 &
1$
#838000
0$
#839000
b10 !
b10 &
1$
#840000
0$
#841000
b11 !
b11 &
1$
#842000
0$
#843000
b100 !
b100 &
1"
1$
#844000
0$
#845000
b101 !
b101 &
1$
#846000
0$
#847000
b110 !
b110 &
1$
#848000
0$
#849000
b111 !
b111 &
1$
#850000
0$
#851000
b1000 !
b1000 &
0"
1$
#852000
0$
#853000
b1001 !
b1001 &
1$
#854000
0$
#855000
b1010 !
b1010 &
1$
#856000
0$
#857000
b1011 !
b1011 &
1$
#858000
0$
#859000
b1100 !
b1100 &
1$
#860000
0$
#861000
b1101 !
b1101 &
1$
#862000
0$
#863000
b1110 !
b1110 &
1$
#864000
0$
#865000
b1111 !
b1111 &
1$
#866000
0$
#867000
b0 !
b0 &
1$
#868000
0$
#869000
b1 !
b1 &
1$
#870000
0$
#871000
b10 !
b10 &
1$
#872000
0$
#873000
b11 !
b11 &
1$
#874000
0$
#875000
b100 !
b100 &
1"
1$
#876000
0$
#877000
b101 !
b101 &
1$
#878000
0$
#879000
b110 !
b110 &
1$
#880000
0$
#881000
b111 !
b111 &
1$
#882000
0$
#883000
b1000 !
b1000 &
0"
1$
#884000
0$
#885000
b1001 !
b1001 &
1$
#886000
0$
#887000
b1010 !
b1010 &
1$
#888000
0$
#889000
b1011 !
b1011 &
1$
#890000
0$
#891000
b1100 !
b1100 &
1$
#892000
0$
#893000
b1101 !
b1101 &
1$
#894000
0$
#895000
b1110 !
b1110 &
1$
#896000
0$
#897000
b1111 !
b1111 &
1$
#898000
0$
#899000
b0 !
b0 &
1$
#900000
0$
#901000
b1 !
b1 &
1$
#902000
0$
#903000
b10 !
b10 &
1$
#904000
0$
#905000
b11 !
b11 &
1$
#906000
0$
#907000
b100 !
b100 &
1"
1$
#908000
0$
#909000
b101 !
b101 &
1$
#910000
0$
#911000
b110 !
b110 &
1$
#912000
0$
#913000
b111 !
b111 &
1$
#914000
0$
#915000
b1000 !
b1000 &
0"
1$
#916000
0$
#917000
b1001 !
b1001 &
1$
#918000
0$
#919000
b1010 !
b1010 &
1$
#920000
0$
#921000
b1011 !
b1011 &
1$
#922000
0$
#923000
b1100 !
b1100 &
1$
#924000
0$
#925000
b1101 !
b1101 &
1$
#926000
0$
#927000
b1110 !
b1110 &
1$
#928000
0$
#929000
b1111 !
b1111 &
1$
#930000
0$
#931000
b0 !
b0 &
1$
#932000
0$
#933000
b1 !
b1 &
1$
#934000
0$
#935000
b10 !
b10 &
1$
#936000
0$
#937000
b11 !
b11 &
1$
#938000
0$
#939000
b100 !
b100 &
1"
1$
#940000
0$
#941000
b101 !
b101 &
1$
#942000
0$
#943000
b110 !
b110 &
1$
#944000
0$
#945000
b111 !
b111 &
1$
#946000
0$
#947000
b1000 !
b1000 &
0"
1$
#948000
0$
#949000
b1001 !
b1001 &
1$
#950000
0$
#951000
b1010 !
b1010 &
1$
#952000
0$
#953000
b1011 !
b1011 &
1$
#954000
0$
#955000
b1100 !
b1100 &
1$
#956000
0$
#957000
b1101 !
b1101 &
1$
#958000
0$
#959000
b1110 !
b1110 &
1$
#960000
0$
#961000
b1111 !
b1111 &
1$
#962000
0$
#963000
b0 !
b0 &
1$
#964000
0$
#965000
b1 !
b1 &
1$
#966000
0$
#967000
b10 !
b10 &
1$
#968000
0$
#969000
b11 !
b11 &
1$
#970000
0$
#971000
b100 !
b100 &
1"
1$
#972000
0$
#973000
b101 !
b101 &
1$
#974000
0$
#975000
b110 !
b110 &
1$
#976000
0$
#977000
b111 !
b111 &
1$
#978000
0$
#979000
b1000 !
b1000 &
0"
1$
#980000
0$
#981000
b1001 !
b1001 &
1$
#982000
0$
#983000
b1010 !
b1010 &
1$
#984000
0$
#985000
b1011 !
b1011 &
1$
#986000
0$
#987000
b1100 !
b1100 &
1$
#988000
0$
#989000
b1101 !
b1101 &
1$
#990000
0$
#991000
b1110 !
b1110 &
1$
#992000
0$
#993000
b1111 !
b1111 &
1$
#994000
0$
#995000
b0 !
b0 &
1$
#996000
0$
#997000
b1 !
b1 &
1$
#998000
0$
#999000
b10 !
b10 &
1$
#1000000
0$
#1001000
b11 !
b11 &
1$
#1002000
0$
#1003000
b100 !
b100 &
1"
1$
#1004000
0$
#1005000
b101 !
b101 &
1$
#1006000
0$
#1007000
b110 !
b110 &
1$
#1008000
0$
#1009000
b111 !
b111 &
1$
#1010000
0$
#1011000
b1000 !
b1000 &
0"
1$
#1012000
0$
#1013000
b1001 !
b1001 &
1$
#1014000
0$
#1015000
b1010 !
b1010 &
1$
#1016000
0$
#1017000
b1011 !
b1011 &
1$
#1018000
0$
#1019000
b1100 !
b1100 &
1$
#1020000
0$
#1021000
b1101 !
b1101 &
1$
#1022000
0$
#1023000
b1110 !
b1110 &
1$
#1024000
0$
#1025000
b1111 !
b1111 &
1$
#1026000
0$
#1027000
b0 !
b0 &
1$
#1028000
0$
#1029000
b1 !
b1 &
1$
#1030000
0$
#1031000
b10 !
b10 &
1$
#1032000
0$
#1033000
b11 !
b11 &
1$
#1034000
0$
#1035000
b100 !
b100 &
1"
1$
#1036000
0$
#1037000
b101 !
b101 &
1$
#1038000
0$
#1039000
b110 !
b110 &
1$
#1040000
0$
#1041000
b111 !
b111 &
1$
#1042000
0$
#1043000
b1000 !
b1000 &
0"
1$
#1044000
0$
#1045000
b1001 !
b1001 &
1$
#1046000
0$
#1047000
b1010 !
b1010 &
1$
#1048000
0$
#1049000
b1011 !
b1011 &
1$
#1050000
0$
#1051000
b1100 !
b1100 &
1$
#1052000
0$
#1053000
b1101 !
b1101 &
1$
#1054000
0$
#1055000
b1110 !
b1110 &
1$
#1056000
0$
#1057000
b1111 !
b1111 &
1$
#1058000
0$
#1059000
b0 !
b0 &
1$
#1060000
0$
#1061000
b1 !
b1 &
1$
#1062000
0$
#1063000
b10 !
b10 &
1$
#1064000
0$
#1065000
b11 !
b11 &
1$
#1066000
0$
#1067000
b100 !
b100 &
1"
1$
#1068000
0$
#1069000
b101 !
b101 &
1$
#1070000
0$
#1071000
b110 !
b110 &
1$
#1072000
0$
#1073000
b111 !
b111 &
1$
#1074000
0$
#1075000
b1000 !
b1000 &
0"
1$
#1076000
0$
#1077000
b1001 !
b1001 &
1$
#1078000
0$
#1079000
b1010 !
b1010 &
1$
#1080000
0$
#1081000
b1011 !
b1011 &
1$
#1082000
0$
#1083000
b1100 !
b1100 &
1$
#1084000
0$
#1085000
b1101 !
b1101 &
1$
#1086000
0$
#1087000
b1110 !
b1110 &
1$
#1088000
0$
#1089000
b1111 !
b1111 &
1$
#1090000
0$
#1091000
b0 !
b0 &
1$
#1092000
0$
#1093000
b1 !
b1 &
1$
#1094000
0$
#1095000
b10 !
b10 &
1$
#1096000
0$
#1097000
b11 !
b11 &
1$
#1098000
0$
#1099000
b100 !
b100 &
1"
1$
