mux21a/mux21a.v
module mux21a (
    a, b, out, clk
);
    input  a, b, clk;
    output out;
    reg out;
    always @(a or b or clk)
        if( clk == 0 ) 
            out = a;
        else 
            out = b;
            
endmodule

mux21a/tb_mux21a.v
//~ `New testbench
`timescale  100ns / 1ns
`include "mux21a.v"

module tb_mux21a;

// first Parameters
parameter PERIOD  = 10;


// first Inputs
reg   a                                    = 1 ;
reg   b                                    = 0 ;
reg   clk                                   = 0 ;
// first Outputs
wire  out                                  ;


initial
begin
    forever #(PERIOD/2)  clk=~clk;
end

// initial
// begin
//     #(PERIOD*2) rst_n  =  1;
// end

mux21a  u_mux21a (
    .a                       ( a     ),
    .b                       ( b     ),
    .clk                     ( clk    ),

    .out                     ( out   )
);

initial
begin
    $dumpfile("wave.vcd");        //生成的vcd文件名称
    $dumpvars;
    #50
    a = 1'b1;
    b = 1'b0;
    $finish;
end

endmodule

mux21a/wave.vcd
$date
	Thu Nov  9 21:04:17 2023
$end
$version
	Icarus Verilog
$end
$timescale
	1ns
$end
$scope module tb_mux21a $end
$var wire 1 ! out $end
$var parameter 32 " PERIOD $end
$var reg 1 # a $end
$var reg 1 $ b $end
$var reg 1 % clk $end
$scope module u_mux21a $end
$var wire 1 # a $end
$var wire 1 $ b $end
$var wire 1 % clk $end
$var reg 1 ! out $end
$upscope $end
$upscope $end
$enddefinitions $end
$comment Show the parameter values. $end
$dumpall
b1010 "
$end
#0
$dumpvars
0%
0$
1#
1!
$end
#500
0!
1%
#1000
1!
0%
#1500
0!
1%
#2000
1!
0%
#2500
0!
1%
#3000
1!
0%
#3500
0!
1%
#4000
1!
0%
#4500
0!
1%
#5000
1!
0%
